odoo/addons/l10n_it_withholding_tax/README.rst
odoo/addons/l10n_it_withholding_tax/__init__.py
odoo/addons/l10n_it_withholding_tax/__manifest__.py
odoo/addons/l10n_it_withholding_tax/i18n/de.po
odoo/addons/l10n_it_withholding_tax/i18n/de_DE.po
odoo/addons/l10n_it_withholding_tax/i18n/it.po
odoo/addons/l10n_it_withholding_tax/i18n/l10n_it_withholding_tax.pot
odoo/addons/l10n_it_withholding_tax/migrations/13.0.1.0.0/noupdate_changes.xml
odoo/addons/l10n_it_withholding_tax/migrations/13.0.1.0.0/post-migration.py
odoo/addons/l10n_it_withholding_tax/migrations/13.0.1.0.0/pre-migration.py
odoo/addons/l10n_it_withholding_tax/migrations/16.0.1.2.0/post-migrate.py
odoo/addons/l10n_it_withholding_tax/models/__init__.py
odoo/addons/l10n_it_withholding_tax/models/account.py
odoo/addons/l10n_it_withholding_tax/models/withholding_tax.py
odoo/addons/l10n_it_withholding_tax/readme/CONTRIBUTORS.md
odoo/addons/l10n_it_withholding_tax/readme/DESCRIPTION.md
odoo/addons/l10n_it_withholding_tax/readme/ROADMAP.md
odoo/addons/l10n_it_withholding_tax/readme/USAGE.md
odoo/addons/l10n_it_withholding_tax/security/ir.model.access.csv
odoo/addons/l10n_it_withholding_tax/security/security.xml
odoo/addons/l10n_it_withholding_tax/static/description/icon.png
odoo/addons/l10n_it_withholding_tax/static/description/index.html
odoo/addons/l10n_it_withholding_tax/static/img/fattura-fornitore-768x517.png
odoo/addons/l10n_it_withholding_tax/static/img/foto-3-1-1024x505.png
odoo/addons/l10n_it_withholding_tax/static/img/pagamento-fattura-fornitore.png
odoo/addons/l10n_it_withholding_tax/static/img/pagamento-ritenuta.png
odoo/addons/l10n_it_withholding_tax/static/img/ritenuta-acconto-odoo-codifica-768x457.png
odoo/addons/l10n_it_withholding_tax/static/src/components/account_payment_field/account_payment.xml
odoo/addons/l10n_it_withholding_tax/tests/__init__.py
odoo/addons/l10n_it_withholding_tax/tests/test_withholding_tax.py
odoo/addons/l10n_it_withholding_tax/views/account.xml
odoo_addon_l10n_it_withholding_tax-16.0.1.2.2.dist-info/METADATA
odoo_addon_l10n_it_withholding_tax-16.0.1.2.2.dist-info/WHEEL
odoo_addon_l10n_it_withholding_tax-16.0.1.2.2.dist-info/top_level.txt
odoo_addon_l10n_it_withholding_tax-16.0.1.2.2.dist-info/RECORD
