Metadata-Version: 2.1
Name: odoo-addon-l10n_it_withholding_tax
Version: 16.0.1.2.2
Requires-Python: >=3.10
Requires-Dist: odoo>=16.0a,<16.1dev
Summary: ITA - Ritenute d'acconto
Home-page: https://github.com/OCA/l10n-italy
License: AGPL-3
Author: Openforce, Odoo Italia Network, Odoo Community Association (OCA)
Author-email: support@odoo-community.org
Classifier: Programming Language :: Python
Classifier: Framework :: Odoo
Classifier: Framework :: Odoo :: 16.0
Classifier: License :: OSI Approved :: GNU Affero General Public License v3
Classifier: Development Status :: 4 - Beta
